fc_xd_bigdata.py
fc_bigdata-1.0.dist-info/METADATA
fc_bigdata-1.0.dist-info/WHEEL
fc_bigdata-1.0.dist-info/top_level.txt
fc_bigdata-1.0.dist-info/RECORD
