Metadata-Version: 2.1
Name: fc-bigdata
Version: 1.0
Summary: 大数据
Home-page: UNKNOWN
Author: 大数据
Author-email: fc@bigdata.com
License: UNKNOWN
Platform: UNKNOWN
